kloppy/__init__.py
kloppy/cmdline.py
kloppy/config.py
kloppy/datafactory.py
kloppy/event_pattern_matching.py
kloppy/exceptions.py
kloppy/hawkeye.py
kloppy/helpers.py
kloppy/impect.py
kloppy/io.py
kloppy/metrica.py
kloppy/opta.py
kloppy/pff.py
kloppy/secondspectrum.py
kloppy/signality.py
kloppy/skillcorner.py
kloppy/sportec.py
kloppy/sportscode.py
kloppy/statsbomb.py
kloppy/statsperform.py
kloppy/tracab.py
kloppy/utils.py
kloppy/wyscout.py
kloppy/_providers/__init__.py
kloppy/_providers/datafactory.py
kloppy/_providers/hawkeye.py
kloppy/_providers/impect.py
kloppy/_providers/metrica.py
kloppy/_providers/opta.py
kloppy/_providers/pff.py
kloppy/_providers/secondspectrum.py
kloppy/_providers/signality.py
kloppy/_providers/skillcorner.py
kloppy/_providers/sportec.py
kloppy/_providers/sportscode.py
kloppy/_providers/statsbomb.py
kloppy/_providers/statsperform.py
kloppy/_providers/tracab.py
kloppy/_providers/wyscout.py
kloppy/domain/__init__.py
kloppy/domain/models/__init__.py
kloppy/domain/models/code.py
kloppy/domain/models/common.py
kloppy/domain/models/event.py
kloppy/domain/models/formation.py
kloppy/domain/models/pitch.py
kloppy/domain/models/position.py
kloppy/domain/models/time.py
kloppy/domain/models/tracking.py
kloppy/domain/models/statsbomb/__init__.py
kloppy/domain/models/statsbomb/event.py
kloppy/domain/services/__init__.py
kloppy/domain/services/event_factory.py
kloppy/domain/services/frame_factory.py
kloppy/domain/services/aggregators/__init__.py
kloppy/domain/services/aggregators/aggregator.py
kloppy/domain/services/aggregators/minutes_played.py
kloppy/domain/services/matchers/__init__.py
kloppy/domain/services/matchers/css.py
kloppy/domain/services/matchers/pattern/__init__.py
kloppy/domain/services/matchers/pattern/event.py
kloppy/domain/services/matchers/pattern/regexp/__init__.py
kloppy/domain/services/matchers/pattern/regexp/ast.py
kloppy/domain/services/matchers/pattern/regexp/matchers.py
kloppy/domain/services/matchers/pattern/regexp/regexp.py
kloppy-3.18.0.dist-info/LICENSE
kloppy-3.18.0.dist-info/METADATA
kloppy-3.18.0.dist-info/WHEEL
kloppy-3.18.0.dist-info/entry_points.txt
kloppy-3.18.0.dist-info/top_level.txt
kloppy-3.18.0.dist-info/RECORD
