Metadata-Version: 2.1
Name: kloppy
Version: 3.18.0
Summary: Standardizing soccer tracking- and event data
Home-page: https://kloppy.pysport.org/
Author: Koen Vossen
Author-email: info@koenvossen.nl
License: BSD
Classifier: Intended Audience :: Developers
Classifier: Intended Audience :: Science/Research
Classifier: Programming Language :: Python :: 3
Classifier: Programming Language :: Python :: 3.8
Classifier: Programming Language :: Python :: 3.9
Classifier: Programming Language :: Python :: 3.10
Classifier: Programming Language :: Python :: 3.11
Classifier: Programming Language :: Python :: 3.12
Classifier: License :: OSI Approved
Classifier: Topic :: Scientific/Engineering
License-File: LICENSE
Requires-Dist: lxml>=4.4.0
Requires-Dist: pytz>=2020.1
Requires-Dist: sortedcontainers>=2
Requires-Dist: fsspec[http]>=2024.12.0
Requires-Dist: typing-extensions; python_version < "3.11"
Requires-Dist: fsspec[http]<=2025.3.0; python_version <= "3.8"
Provides-Extra: development
Requires-Dist: pre-commit==2.6.0; extra == "development"
Provides-Extra: query
Requires-Dist: networkx<3,>=2.4; extra == "query"
Provides-Extra: test
Requires-Dist: pytest<8,>=6.2.5; extra == "test"
Requires-Dist: pandas>=2; extra == "test"
Requires-Dist: black==22.3.0; extra == "test"
Requires-Dist: polars>=0.16.6; extra == "test"
Requires-Dist: pyarrow; extra == "test"
Requires-Dist: pytest-lazy-fixture; extra == "test"
Requires-Dist: s3fs; extra == "test"
Requires-Dist: moto[s3]; extra == "test"
Requires-Dist: flask; extra == "test"
Requires-Dist: flask-cors; extra == "test"
Requires-Dist: pytest-httpserver; extra == "test"
